{
    "DOI": "10.3866/PKU.WHXB20110908",
    "adsorbentMaterial": [
        "[Sr(BDC) (H2O)]"
    ],
    "adsorbents": [
        {
            "hashkey": "NIST-MATDB-45f7a8a7fe7da4b2418a395523ccc17f",
            "name": "[Sr(BDC) (H2O)]"
        }
    ],
    "authors": [
        "Ying Fu",
        "Guo-Bao Li",
        "Fu-Hui Liao",
        "Jian-Hua Lin"
    ],
    "categories": [
        "exp"
    ],
    "isotherms": [],
    "journal": "Acta Physico-Chimica Sinica",
    "temperatures": [],
    "title": "Synthesis, Structure and Thermal Property of a 3D Coordination Polymer [Sr(BDC)(H2O)]",
    "year": 2011
}
